Workbook

Sheet 01_계약입력
A1: 계약ID | B1: 계약형태 | C1: 규모 | D1: 시작월 | E1: 종료월 | F1: 항로 | G1: 운임결정방식 | H1: 운임Benchmark | I1: 고정운임 | J1: 운임노출방향 | K1: 연간노출일수(days) | L1: 연료부담주체 | M1: 비고
A2: A | B2: Index-linked TC-out | C2: 4척 | D2: 1월 | E2: 12월 | F2: Panamax 글로벌 TC | G2: P5TC 100% 연동 | H2: P5TC | J2: 운임 하락 | K2: 1440 | L2: 용선자 | M2: 4척×360일, 지수 하락 시 수입 감소
A3: B | B3: Fixed TC-out | C3: 5척 | D3: 1월 | E3: 12월 | F3: Panamax 글로벌 TC | G3: 고정 일일용선료 | I3: 16000 USD/day | J3: 거의 없음 | K3: 1800 | L3: 용선자 | M3: 5척×360일, 운임 및 연료가격 노출 제한
A4: C1 | B4: Spot/Voyage | C4: 1척 | D4: 1월 | E4: 12월 | F4: PNW→일본 곡물 | G4: 시장 Voyage 운임 | H4: P3A-equivalent | J4: 운임 하락 | K4: 360 | L4: BlueWave | M4: 연 8항차, P3A는 Cross-hedge 후보 Benchmark
A5: C2 | B5: Spot/Voyage | C5: 1척 | D5: 1월 | E5: 12월 | F5: US Gulf→일본 곡물 | G5: 시장 Voyage 운임 | H5: P7-equivalent | J5: 운임 하락 | K5: 320 | L5: BlueWave | M5: 연 4항차, P7은 US Gulf→동아시아 곡물 Benchmark
A6: D | B6: COA | C6: 연 4항차 | D6: 2월 | E6: 11월 | F6: US Gulf→동북아 곡물 | G6: 화주 운임 고정 | H6: Cross-hedge 추후 결정 | I6: 55 USD/t | J6: 운임 상승 | K6: 180 | L6: BlueWave | M6: 2·5·8·11월 운송, 선박은 운송 시점에 TC-in

Sheet 02_연료입력
A1: 계약ID | B1: 급유지역 | C1: 유종 | D1: 구매시점 | E1: 항차당예상수량(t) | F1: 연간항차수 | G1: 연간예상수량(t) | H1: 가격위험Proxy | I1: 비고
A2: C1 | B2: Vancouver/PNW | C2: VLSFO 0.5% | D2: 항차별 | E2: 1000 | F2: 8 | G2: 8000 | H2: Brent Crude | I2: 프로토타입에서는 Brent 가격변동으로 연료가격위험 대리
A3: C2 | B3: US Gulf | C3: VLSFO 0.5% | D3: 항차별 | E3: 1800 | F3: 4 | G3: 7200 | H3: Brent Crude | I3: 프로토타입에서는 Brent 가격변동으로 연료가격위험 대리
A4: D | B4: US Gulf | C4: VLSFO 0.5% | D4: 항차별 | E4: 1050 | F4: 4 | G4: 4200 | H4: Brent Crude | I4: 프로토타입에서는 Brent 가격변동으로 연료가격위험 대리
A5: 합계 | F5: 16 | G5: 19400

Sheet 03_COA일정
A1: 항차ID | B1: 계약ID | C1: 출항월 | D1: 후속월 | E1: 선박조달노출_출항월(days) | F1: 선박조달노출_후속월(days) | G1: USGC VLSFO_출항월(t) | H1: 화물량(t) | I1: 고정운임(USD/t) | J1: 비고
A2: D1 | B2: D | C2: 2월 | D2: 3월 | E2: -30 | F2: -15 | G2: 1050 | H2: 66000 | I2: 55 | J2: US Gulf→동북아
A3: D2 | B3: D | C3: 5월 | D3: 6월 | E3: -30 | F3: -15 | G3: 1050 | H3: 66000 | I3: 55 | J3: US Gulf→동북아
A4: D3 | B4: D | C4: 8월 | D4: 9월 | E4: -30 | F4: -15 | G4: 1050 | H4: 66000 | I4: 55 | J4: US Gulf→동북아
A5: D4 | B5: D | C5: 11월 | D5: 12월 | E5: -30 | F5: -15 | G5: 1050 | H5: 66000 | I5: 55 | J5: US Gulf→동북아

Sheet 04_월별노출
A1: 월 | B1: A_P5TC노출(days) | C1: C1_PNW일본_운임노출(t) | D1: C2_P7_운임노출(t) | E1: D_선박조달노출(days) | F1: 연료구매노출(t)
A2: 1월 | B2: 120 | C2: 66000 | D2: 66000 | E2: 0 | F2: 2800
A3: 2월 | B3: 120 | C3: 66000 | D3: 0 | E3: -30 | F3: 2050
A4: 3월 | B4: 120 | C4: 0 | D4: 0 | E4: -15 | F4: 0
A5: 4월 | B5: 120 | C5: 66000 | D5: 66000 | E5: 0 | F5: 2800
A6: 5월 | B6: 120 | C6: 66000 | D6: 0 | E6: -30 | F6: 2050
A7: 6월 | B7: 120 | C7: 66000 | D7: 0 | E7: -15 | F7: 1000
A8: 7월 | B8: 120 | C8: 0 | D8: 66000 | E8: 0 | F8: 1800
A9: 8월 | B9: 120 | C9: 66000 | D9: 0 | E9: -30 | F9: 2050
A10: 9월 | B10: 120 | C10: 66000 | D10: 0 | E10: -15 | F10: 1000
A11: 10월 | B11: 120 | C11: 0 | D11: 66000 | E11: 0 | F11: 1800
A12: 11월 | B12: 120 | C12: 66000 | D12: 0 | E12: -30 | F12: 2050
A13: 12월 | B13: 120 | C13: 0 | D13: 0 | E13: -15 | F13: 0
A14: 연간합계 | B14: 1440 | C14: 528000 | D14: 264000 | E14: -180 | F14: 19400

Sheet 05_재무입력
A1: 항목 | B1: 금액(USD) | C1: 구분 | D1: 모형사용 | E1: 용도/비고
A2: 현금및현금성자산 | B2: 20315532 | C2: EuroDry 2025 실제 | D2: 사용 | E2: 기초 가용현금
A3: 유동 제한현금 | B3: 2156922 | C3: EuroDry 2025 실제 | D3: 참고 | E3: 자유로운 헤지재원에서 제외
A4: 비유동 제한현금 | B4: 3200000 | C4: EuroDry 2025 실제 | D4: 참고 | E4: 자유로운 헤지재원에서 제외
A5: 유동부채 | B5: 18723489 | C5: EuroDry 2025 실제 | D5: 참고 | E5: 유동성 상태 확인용, 전액 직접 차감하지 않음
A6: 2026년 대출원금상환 | B6: 12275000 | C6: EuroDry 실제 계약 | D6: 사용 | E6: 향후 1년 필수 현금유출
A7: 2026년 신조선 지급약정 | B7: 10774773 | C7: EuroDry 실제 계약 | D7: 사용 | E7: 외부조달이 없는 부분은 자체현금 유출
A8: 2025년 영업현금흐름 | B8: 12760620 | C8: EuroDry 2025 실제 | D8: 초기사용 | E8: 초기 Proxy, 이후 BlueWave 산출 CF로 교체
A9: 최소유동성 Floor | B9: 10500000 | C9: 모형 가정 | D9: 사용 | E9: 약 3개월 반복 현금비용을 감당하기 위한 최소 유동성
A10: 확정 외부조달액 | B10: 4000000 | C10: BlueWave 모형 가정 | D10: 사용 | E10: 신조선 CAPEX 중 일부를 외부 금융조달하는 중간 재무상태 시나리오

Sheet 06_월별현금흐름
A1: 월 | B1: 월초현금 | C1: 기준영업CF | D1: 시장충격조정_무헤지 | E1: 헤지정산CF | F1: 증거금·담보증가액 | G1: 확정외부조달 | H1: 대출원금상환 | I1: CAPEX지급 | J1: 월말현금 | K1: 최소유동성Floor | L1: Floor여유액 | M1: Floor충족여부
A2: 1월 | B2: ='05_재무입력'!$B$2 -> 20315532 | C2: ='05_재무입력'!$B$8/12 -> 1063385 | D2: ='12_월별시장충격'!H2 -> -786602.34 | E2: 0 | F2: 0 | G2: 0 | H2: 0 | I2: 0 | J2: =B2+C2+D2+E2-F2+G2-H2-I2 -> 20592315 | K2: ='05_재무입력'!$B$9 -> 10500000 | L2: =J2-K2 -> 10092315 | M2: =IF(J2>=K2,"충족","미달") -> 충족
A3: 2월 | B3: =J2 -> 20592315 | C3: ='05_재무입력'!$B$8/12 -> 1063385 | D3: ='12_월별시장충격'!H3 -> -611051.29 | E3: 0 | F3: 0 | G3: 0 | H3: 0 | I3: 0 | J3: =B3+C3+D3+E3-F3+G3-H3-I3 -> 21044648 | K3: ='05_재무입력'!$B$9 -> 10500000 | L3: =J3-K3 -> 10544648 | M3: =IF(J3>=K3,"충족","미달") -> 충족
A4: 3월 | B4: =J3 -> 21044648 | C4: ='05_재무입력'!$B$8/12 -> 1063385 | D4: ='12_월별시장충격'!H4 -> -352174.06 | E4: 0 | F4: 0 | G4: 0 | H4: ='05_재무입력'!$B$6/4 -> 3068750 | I4: 0 | J4: =B4+C4+D4+E4-F4+G4-H4-I4 -> 18687109 | K4: ='05_재무입력'!$B$9 -> 10500000 | L4: =J4-K4 -> 8187109.3 | M4: =IF(J4>=K4,"충족","미달") -> 충족
A5: 4월 | B5: =J4 -> 18687109 | C5: ='05_재무입력'!$B$8/12 -> 1063385 | D5: ='12_월별시장충격'!H5 -> -786602.34 | E5: 0 | F5: 0 | G5: 0 | H5: 0 | I5: 0 | J5: =B5+C5+D5+E5-F5+G5-H5-I5 -> 18963892 | K5: ='05_재무입력'!$B$9 -> 10500000 | L5: =J5-K5 -> 8463892 | M5: =IF(J5>=K5,"충족","미달") -> 충족
A6: 5월 | B6: =J5 -> 18963892 | C6: ='05_재무입력'!$B$8/12 -> 1063385 | D6: ='12_월별시장충격'!H6 -> -611051.29 | E6: 0 | F6: 0 | G6: 0 | H6: 0 | I6: 0 | J6: =B6+C6+D6+E6-F6+G6-H6-I6 -> 19416226 | K6: ='05_재무입력'!$B$9 -> 10500000 | L6: =J6-K6 -> 8916225.7 | M6: =IF(J6>=K6,"충족","미달") -> 충족
A7: 6월 | B7: =J6 -> 19416226 | C7: ='05_재무입력'!$B$8/12 -> 1063385 | D7: ='12_월별시장충격'!H7 -> -520088.19 | E7: 0 | F7: 0 | G7: ='05_재무입력'!$B$10/2 -> 2000000 | H7: ='05_재무입력'!$B$6/4 -> 3068750 | I7: ='05_재무입력'!$B$7/2 -> 5387386.5 | J7: =B7+C7+D7+E7-F7+G7-H7-I7 -> 13503386 | K7: ='05_재무입력'!$B$9 -> 10500000 | L7: =J7-K7 -> 3003386 | M7: =IF(J7>=K7,"충족","미달") -> 충족
A8: 7월 | B8: =J7 -> 13503386 | C8: ='05_재무입력'!$B$8/12 -> 1063385 | D8: ='12_월별시장충격'!H8 -> -618688.21 | E8: 0 | F8: 0 | G8: 0 | H8: 0 | I8: 0 | J8: =B8+C8+D8+E8-F8+G8-H8-I8 -> 13948083 | K8: ='05_재무입력'!$B$9 -> 10500000 | L8: =J8-K8 -> 3448082.8 | M8: =IF(J8>=K8,"충족","미달") -> 충족
A9: 8월 | B9: =J8 -> 13948083 | C9: ='05_재무입력'!$B$8/12 -> 1063385 | D9: ='12_월별시장충격'!H9 -> -611051.29 | E9: 0 | F9: 0 | G9: 0 | H9: 0 | I9: 0 | J9: =B9+C9+D9+E9-F9+G9-H9-I9 -> 14400416 | K9: ='05_재무입력'!$B$9 -> 10500000 | L9: =J9-K9 -> 3900416.5 | M9: =IF(J9>=K9,"충족","미달") -> 충족
A10: 9월 | B10: =J9 -> 14400416 | C10: ='05_재무입력'!$B$8/12 -> 1063385 | D10: ='12_월별시장충격'!H10 -> -520088.19 | E10: 0 | F10: 0 | G10: 0 | H10: ='05_재무입력'!$B$6/4 -> 3068750 | I10: 0 | J10: =B10+C10+D10+E10-F10+G10-H10-I10 -> 11874963 | K10: ='05_재무입력'!$B$9 -> 10500000 | L10: =J10-K10 -> 1374963.3 | M10: =IF(J10>=K10,"충족","미달") -> 충족
A11: 10월 | B11: =J10 -> 11874963 | C11: ='05_재무입력'!$B$8/12 -> 1063385 | D11: ='12_월별시장충격'!H11 -> -618688.21 | E11: 0 | F11: 0 | G11: 0 | H11: 0 | I11: 0 | J11: =B11+C11+D11+E11-F11+G11-H11-I11 -> 12319660 | K11: ='05_재무입력'!$B$9 -> 10500000 | L11: =J11-K11 -> 1819660.1 | M11: =IF(J11>=K11,"충족","미달") -> 충족
A12: 11월 | B12: =J11 -> 12319660 | C12: ='05_재무입력'!$B$8/12 -> 1063385 | D12: ='12_월별시장충격'!H12 -> -611051.29 | E12: 0 | F12: 0 | G12: 0 | H12: 0 | I12: 0 | J12: =B12+C12+D12+E12-F12+G12-H12-I12 -> 12771994 | K12: ='05_재무입력'!$B$9 -> 10500000 | L12: =J12-K12 -> 2271993.8 | M12: =IF(J12>=K12,"충족","미달") -> 충족
A13: 12월 | B13: =J12 -> 12771994 | C13: ='05_재무입력'!$B$8/12 -> 1063385 | D13: ='12_월별시장충격'!H13 -> -352174.06 | E13: 0 | F13: 0 | G13: ='05_재무입력'!$B$10/2 -> 2000000 | H13: ='05_재무입력'!$B$6/4 -> 3068750 | I13: ='05_재무입력'!$B$7/2 -> 5387386.5 | J13: =B13+C13+D13+E13-F13+G13-H13-I13 -> 7027068.2 | K13: ='05_재무입력'!$B$9 -> 10500000 | L13: =J13-K13 -> -3472931.8 | M13: =IF(J13>=K13,"충족","미달") -> 미달
A14: 합계 | C14: =SUM(C2:C13) -> 12760620 | D14: =SUM(D2:D13) -> -6999310.8 | E14: =SUM(E2:E13) -> 0 | F14: =SUM(F2:F13) -> 0 | G14: =SUM(G2:G13) -> 4000000 | H14: =SUM(H2:H13) -> 12275000 | I14: =SUM(I2:I13) -> 10774773

Sheet 07_영업손익입력
A1: 계약ID | B1: 계약형태 | C1: 규모 | D1: 항로 | E1: 연간항차수 | F1: 항차당화물량(t) | G1: 기준운임 | H1: 항차기간(days) | I1: 연간노출일수(days) | J1: 운임Benchmark | K1: 연료비부담 | L1: 비고
A2: A | B2: Index-linked TC-out | C2: 4척 | D2: Panamax 글로벌 | G2: P5TC 100% 연동 | I2: 1440 | J2: P5TC | K2: 용선자 | L2: 4척 각각 360일, 월별 P5TC로 매출 계산
A3: B | B3: Fixed TC-out | C3: 5척 | D3: Panamax 글로벌 | G3: 16000 USD/day | I3: 1800 | K3: 용선자 | L3: 5척 각각 360일 고정 TC
A4: C1 | B4: Spot/Voyage | C4: 1척 | D4: PNW→일본 곡물 | E4: 8 | F4: 66000 | G4: 28 USD/t | H4: 45 | I4: 360 | J4: P3A-equivalent | K4: BlueWave | L4: Voyage 수익은 USD/t, P3A는 Cross-hedge 후보
A5: C2 | B5: Spot/Voyage | C5: 1척 | D5: US Gulf→일본 곡물 | E5: 4 | F5: 66000 | G5: 51 USD/t | H5: 80 | I5: 320 | J5: P7-equivalent | K5: BlueWave | L5: P7은 US Gulf→동아시아 곡물 Benchmark
A6: D | B6: COA | C6: 연 4항차 | D6: US Gulf→동북아 곡물 | E6: 4 | F6: 66000 | G6: 55 USD/t | H6: 45 | I6: 180 | J6: Cross-hedge 추후 결정 | K6: BlueWave | L6: 화주 운임은 고정, 선박은 운송 시점에 TC-in

Sheet 08_항차비용
A1: 계약ID | B1: 연간항차수 | C1: 항차기간(days) | D1: 화물량(t) | E1: 기준운임(USD/t) | F1: 항차매출(USD) | G1: 연료사용량(t) | H1: 급유지역 | I1: 연료단가(USD/t) | J1: 항만·대리점비(USD) | K1: 운하비(USD) | L1: Commission율 | M1: TC-in일수 | N1: TC-in일당(USD/day) | O1: 비고
A2: C1 | B2: 8 | C2: 45 | D2: 66000 | E2: 28 | F2: 1848000 | G2: 1000 | H2: Vancouver/PNW | J2: 150000 | K2: 0 | L2: 0.05 | M2: 0 | O2: PNW→일본, 항만·대리점비는 합성 가정
A3: C2 | B3: 4 | C3: 80 | D3: 66000 | E3: 51 | F3: 3366000 | G3: 1800 | H3: US Gulf | J3: 150000 | K3: 0 | L3: 0.05 | M3: 0 | O3: US Gulf→동북아, Cape of Good Hope 경유
A4: D | B4: 4 | C4: 45 | D4: 66000 | E4: 55 | F4: 3630000 | G4: 1050 | H4: US Gulf | J4: 150000 | K4: 0 | L4: 0.05 | M4: 45 | O4: US Gulf→동북아, Cape 경유, TC-in 수행

Sheet 09_고정운영비
A1: 항목 | B1: 기준단가 | C1: 대상 | D1: 계산기준 | E1: 연간금액(USD) | F1: 비고
A2: 자사선 Vessel Operating Expense | B2: 5692 USD/day | C2: 11척 | D2: 11척×365일 | E2: 22853380 | F2: EuroDry 2025 실제 일평균
A3: 선박 Management Fee | B3: 1007 USD/day | C3: 11척 | D3: 11척×365일 | E3: 4043105 | F3: EuroDry 2025 실제 일평균
A4: 본사 G&A | B4: 3171053 USD/year | C4: 회사 전체 | D4: 연간 | E4: 3171053 | F4: EuroDry 2025 실제
A5: Drydocking | B5: 0 | C5: 별도 시나리오 | D5: 기준 시나리오 제외 | E5: 0 | F5: 필요 시 특정 월 스트레스 항목으로 추가
A6: 합계 | E6: 30067538

Sheet 10_기준시장값
A1: 위험요인ID | B1: 위험요인 | C1: 단위 | D1: 기준값 | E1: 기준기간 | F1: 데이터구분 | G1: 적용계약 | H1: 비고
A2: FRT_A | B2: Panamax P5TC | C2: USD/day | D2: 13361 | E2: 2025 연평균 | F2: 실제 시장자료 | G2: A | H2: Index-linked TC-out 운임위험 기준
A3: FRT_C1 | B3: PNW→Japan 곡물운임 | C3: USD/t | D3: 28.05 | E3: 2025 연평균 | F3: USDA 실제자료 | G3: C1 | H3: 실제 Voyage 운임위험 기준
A4: FRT_C2 | B4: US Gulf→Japan 곡물운임 | C4: USD/t | D4: 50.84 | E4: 2025 연평균 | F4: USDA 실제자료 | G4: C2 | H4: P7-equivalent 물리운임 기준
A5: TCIN_D | B5: Panamax TC-in 조달비 Proxy | C5: USD/day | D5: 13876.14 | E5: 2025 연평균 | F5: KOBC 실제자료 | G5: D | H5: KOBC Panamax TC Average 2025 일별평균. D의 미래 TC-in 조달비 기준
A6: FUEL_BASE | B6: VLSFO 기준연료비 (Brent 변동률 Proxy) | C6: USD/t | D6: 535 | E6: 2025 연평균 | F6: 임시 Proxy | G6: C1,C2,D | H6: VLSFO 기준비용 $535/t에 Brent 변동률을 적용하는 MVP Proxy. 실제 VLSFO/파생상품 데이터는 후속 고도화
A7: COMMISSION | B7: 운임수입 Commission | C7: 비율 | D7: 0.05 | E7: 모형 전체 | F7: 모형가정 | G7: A,C1,C2 | H7: 운임변동에 따른 순현금효과 계산 시 적용

Sheet 11_시장시나리오
A1: 시나리오명 | B1: 역사적_복합스트레스
A2: 설명 | B2: 2022-03~2025-12 실제 시장변동의 10/90 분위수를 이용한 MVP 복합 Stress
A4: 위험요인ID | B4: 기준값 | C4: 충격률 | D4: 충격후값 | E4: 변화량
A5: FRT_A | B5: ='10_기준시장값'!D2 -> 13361 | C5: ='16_역사변동분석'!J4 -> -0.20013719 | D5: =B5*(1+C5) -> 10686.967 | E5: =D5-B5 -> -2674.033
A6: FRT_C1 | B6: ='10_기준시장값'!D3 -> 28.05 | C6: ='16_역사변동분석'!J5 -> -0.071848739 | D6: =B6*(1+C6) -> 26.034643 | E6: =D6-B6 -> -2.0153571
A7: FRT_C2 | B7: ='10_기준시장값'!D4 -> 50.84 | C7: ='16_역사변동분석'!J6 -> -0.07499408 | D7: =B7*(1+C7) -> 47.027301 | E7: =D7-B7 -> -3.812699
A8: TCIN_D | B8: ='10_기준시장값'!D5 -> 13876.14 | C8: ='16_역사변동분석'!J7 -> 0.2274134 | D8: =B8*(1+C8) -> 17031.76 | E8: =D8-B8 -> 3155.6202
A9: FUEL_BRENT | B9: 1 | C9: ='16_역사변동분석'!J8 -> 0.077665863 | D9: =B9*(1+C9) -> 1.0776659 | E9: =D9-B9 -> 0.077665863

Sheet 12_월별시장충격
A1: 월 | B1: A_P5TC충격 | C1: C1_운임충격 | D1: C2_운임충격 | E1: D_TC-in충격 | F1: 연료충격_BrentProxy | G1: 기타시장충격 | H1: 총시장충격
A2: 1월 | B2: ='04_월별노출'!B2*'11_시장시나리오'!$E$5*(1-'10_기준시장값'!$D$7) -> -304839.76 | C2: ='04_월별노출'!C2*'11_시장시나리오'!$E$6*(1-'10_기준시장값'!$D$7) -> -126362.89 | D2: ='04_월별노출'!D2*'11_시장시나리오'!$E$7*(1-'10_기준시장값'!$D$7) -> -239056.23 | E2: ='04_월별노출'!E2*'11_시장시나리오'!$E$8 -> 0 | F2: =-'04_월별노출'!F2*'10_기준시장값'!$D$6*'11_시장시나리오'!$E$9 -> -116343.46 | G2: 0 | H2: =SUM(B2:G2) -> -786602.34
A3: 2월 | B3: ='04_월별노출'!B3*'11_시장시나리오'!$E$5*(1-'10_기준시장값'!$D$7) -> -304839.76 | C3: ='04_월별노출'!C3*'11_시장시나리오'!$E$6*(1-'10_기준시장값'!$D$7) -> -126362.89 | D3: ='04_월별노출'!D3*'11_시장시나리오'!$E$7*(1-'10_기준시장값'!$D$7) -> 0 | E3: ='04_월별노출'!E3*'11_시장시나리오'!$E$8 -> -94668.607 | F3: =-'04_월별노출'!F3*'10_기준시장값'!$D$6*'11_시장시나리오'!$E$9 -> -85180.036 | G3: 0 | H3: =SUM(B3:G3) -> -611051.29
A4: 3월 | B4: ='04_월별노출'!B4*'11_시장시나리오'!$E$5*(1-'10_기준시장값'!$D$7) -> -304839.76 | C4: ='04_월별노출'!C4*'11_시장시나리오'!$E$6*(1-'10_기준시장값'!$D$7) -> 0 | D4: ='04_월별노출'!D4*'11_시장시나리오'!$E$7*(1-'10_기준시장값'!$D$7) -> 0 | E4: ='04_월별노출'!E4*'11_시장시나리오'!$E$8 -> -47334.303 | F4: =-'04_월별노출'!F4*'10_기준시장값'!$D$6*'11_시장시나리오'!$E$9 -> 0 | G4: 0 | H4: =SUM(B4:G4) -> -352174.06
A5: 4월 | B5: ='04_월별노출'!B5*'11_시장시나리오'!$E$5*(1-'10_기준시장값'!$D$7) -> -304839.76 | C5: ='04_월별노출'!C5*'11_시장시나리오'!$E$6*(1-'10_기준시장값'!$D$7) -> -126362.89 | D5: ='04_월별노출'!D5*'11_시장시나리오'!$E$7*(1-'10_기준시장값'!$D$7) -> -239056.23 | E5: ='04_월별노출'!E5*'11_시장시나리오'!$E$8 -> 0 | F5: =-'04_월별노출'!F5*'10_기준시장값'!$D$6*'11_시장시나리오'!$E$9 -> -116343.46 | G5: 0 | H5: =SUM(B5:G5) -> -786602.34
A6: 5월 | B6: ='04_월별노출'!B6*'11_시장시나리오'!$E$5*(1-'10_기준시장값'!$D$7) -> -304839.76 | C6: ='04_월별노출'!C6*'11_시장시나리오'!$E$6*(1-'10_기준시장값'!$D$7) -> -126362.89 | D6: ='04_월별노출'!D6*'11_시장시나리오'!$E$7*(1-'10_기준시장값'!$D$7) -> 0 | E6: ='04_월별노출'!E6*'11_시장시나리오'!$E$8 -> -94668.607 | F6: =-'04_월별노출'!F6*'10_기준시장값'!$D$6*'11_시장시나리오'!$E$9 -> -85180.036 | G6: 0 | H6: =SUM(B6:G6) -> -611051.29
A7: 6월 | B7: ='04_월별노출'!B7*'11_시장시나리오'!$E$5*(1-'10_기준시장값'!$D$7) -> -304839.76 | C7: ='04_월별노출'!C7*'11_시장시나리오'!$E$6*(1-'10_기준시장값'!$D$7) -> -126362.89 | D7: ='04_월별노출'!D7*'11_시장시나리오'!$E$7*(1-'10_기준시장값'!$D$7) -> 0 | E7: ='04_월별노출'!E7*'11_시장시나리오'!$E$8 -> -47334.303 | F7: =-'04_월별노출'!F7*'10_기준시장값'!$D$6*'11_시장시나리오'!$E$9 -> -41551.237 | G7: 0 | H7: =SUM(B7:G7) -> -520088.19
A8: 7월 | B8: ='04_월별노출'!B8*'11_시장시나리오'!$E$5*(1-'10_기준시장값'!$D$7) -> -304839.76 | C8: ='04_월별노출'!C8*'11_시장시나리오'!$E$6*(1-'10_기준시장값'!$D$7) -> 0 | D8: ='04_월별노출'!D8*'11_시장시나리오'!$E$7*(1-'10_기준시장값'!$D$7) -> -239056.23 | E8: ='04_월별노출'!E8*'11_시장시나리오'!$E$8 -> 0 | F8: =-'04_월별노출'!F8*'10_기준시장값'!$D$6*'11_시장시나리오'!$E$9 -> -74792.226 | G8: 0 | H8: =SUM(B8:G8) -> -618688.21
A9: 8월 | B9: ='04_월별노출'!B9*'11_시장시나리오'!$E$5*(1-'10_기준시장값'!$D$7) -> -304839.76 | C9: ='04_월별노출'!C9*'11_시장시나리오'!$E$6*(1-'10_기준시장값'!$D$7) -> -126362.89 | D9: ='04_월별노출'!D9*'11_시장시나리오'!$E$7*(1-'10_기준시장값'!$D$7) -> 0 | E9: ='04_월별노출'!E9*'11_시장시나리오'!$E$8 -> -94668.607 | F9: =-'04_월별노출'!F9*'10_기준시장값'!$D$6*'11_시장시나리오'!$E$9 -> -85180.036 | G9: 0 | H9: =SUM(B9:G9) -> -611051.29
A10: 9월 | B10: ='04_월별노출'!B10*'11_시장시나리오'!$E$5*(1-'10_기준시장값'!$D$7) -> -304839.76 | C10: ='04_월별노출'!C10*'11_시장시나리오'!$E$6*(1-'10_기준시장값'!$D$7) -> -126362.89 | D10: ='04_월별노출'!D10*'11_시장시나리오'!$E$7*(1-'10_기준시장값'!$D$7) -> 0 | E10: ='04_월별노출'!E10*'11_시장시나리오'!$E$8 -> -47334.303 | F10: =-'04_월별노출'!F10*'10_기준시장값'!$D$6*'11_시장시나리오'!$E$9 -> -41551.237 | G10: 0 | H10: =SUM(B10:G10) -> -520088.19
A11: 10월 | B11: ='04_월별노출'!B11*'11_시장시나리오'!$E$5*(1-'10_기준시장값'!$D$7) -> -304839.76 | C11: ='04_월별노출'!C11*'11_시장시나리오'!$E$6*(1-'10_기준시장값'!$D$7) -> 0 | D11: ='04_월별노출'!D11*'11_시장시나리오'!$E$7*(1-'10_기준시장값'!$D$7) -> -239056.23 | E11: ='04_월별노출'!E11*'11_시장시나리오'!$E$8 -> 0 | F11: =-'04_월별노출'!F11*'10_기준시장값'!$D$6*'11_시장시나리오'!$E$9 -> -74792.226 | G11: 0 | H11: =SUM(B11:G11) -> -618688.21
A12: 11월 | B12: ='04_월별노출'!B12*'11_시장시나리오'!$E$5*(1-'10_기준시장값'!$D$7) -> -304839.76 | C12: ='04_월별노출'!C12*'11_시장시나리오'!$E$6*(1-'10_기준시장값'!$D$7) -> -126362.89 | D12: ='04_월별노출'!D12*'11_시장시나리오'!$E$7*(1-'10_기준시장값'!$D$7) -> 0 | E12: ='04_월별노출'!E12*'11_시장시나리오'!$E$8 -> -94668.607 | F12: =-'04_월별노출'!F12*'10_기준시장값'!$D$6*'11_시장시나리오'!$E$9 -> -85180.036 | G12: 0 | H12: =SUM(B12:G12) -> -611051.29
A13: 12월 | B13: ='04_월별노출'!B13*'11_시장시나리오'!$E$5*(1-'10_기준시장값'!$D$7) -> -304839.76 | C13: ='04_월별노출'!C13*'11_시장시나리오'!$E$6*(1-'10_기준시장값'!$D$7) -> 0 | D13: ='04_월별노출'!D13*'11_시장시나리오'!$E$7*(1-'10_기준시장값'!$D$7) -> 0 | E13: ='04_월별노출'!E13*'11_시장시나리오'!$E$8 -> -47334.303 | F13: =-'04_월별노출'!F13*'10_기준시장값'!$D$6*'11_시장시나리오'!$E$9 -> 0 | G13: 0 | H13: =SUM(B13:G13) -> -352174.06
A14: 합계 | B14: =SUM(B2:B13) -> -3658077.1 | C14: =SUM(C2:C13) -> -1010903.1 | D14: =SUM(D2:D13) -> -956224.91 | E14: =SUM(E2:E13) -> -568011.64 | F14: =SUM(F2:F13) -> -806094 | G14: =SUM(G2:G13) -> 0 | H14: =SUM(H2:H13) -> -6999310.8

Sheet 13_Need 진단
A1: 월 | B1: 기준시나리오_월말현금 | C1: 무헤지스트레스_월말현금 | D1: 최소유동성Floor | E1: 구조적유동성부족 | F1: 전체현금부족 | G1: 시장위험기인Need | H1: 누적시장충격 | I1: 필요시장보호율 | J1: 진단
A2: 1월 | B2: ='05_재무입력'!$B$2+'06_월별현금흐름'!C2+'06_월별현금흐름'!G2-'06_월별현금흐름'!H2-'06_월별현금흐름'!I2 -> 21378917 | C2: =B2+SUM('12_월별시장충격'!$H$2:H2) -> 20592315 | D2: ='05_재무입력'!$B$9 -> 10500000 | E2: =MAX(0,D2-B2) -> 0 | F2: =MAX(0,D2-C2) -> 0 | G2: =MAX(0,F2-E2) -> 0 | H2: =SUM('12_월별시장충격'!$H$2:H2) -> -786602.34 | I2: =IF(G2=0,0,G2/ABS(H2)) -> 0 | J2: =IF(AND(E2>0,G2>0),"구조적+시장위험",IF(E2>0,"구조적 유동성",IF(G2>0,"시장위험","충족"))) -> 충족
A3: 2월 | B3: =B2+'06_월별현금흐름'!C3+'06_월별현금흐름'!G3-'06_월별현금흐름'!H3-'06_월별현금흐름'!I3 -> 22442302 | C3: =B3+SUM('12_월별시장충격'!$H$2:H3) -> 21044648 | D3: ='05_재무입력'!$B$9 -> 10500000 | E3: =MAX(0,D3-B3) -> 0 | F3: =MAX(0,D3-C3) -> 0 | G3: =MAX(0,F3-E3) -> 0 | H3: =SUM('12_월별시장충격'!$H$2:H3) -> -1397653.6 | I3: =IF(G3=0,0,G3/ABS(H3)) -> 0 | J3: =IF(AND(E3>0,G3>0),"구조적+시장위험",IF(E3>0,"구조적 유동성",IF(G3>0,"시장위험","충족"))) -> 충족
A4: 3월 | B4: =B3+'06_월별현금흐름'!C4+'06_월별현금흐름'!G4-'06_월별현금흐름'!H4-'06_월별현금흐름'!I4 -> 20436937 | C4: =B4+SUM('12_월별시장충격'!$H$2:H4) -> 18687109 | D4: ='05_재무입력'!$B$9 -> 10500000 | E4: =MAX(0,D4-B4) -> 0 | F4: =MAX(0,D4-C4) -> 0 | G4: =MAX(0,F4-E4) -> 0 | H4: =SUM('12_월별시장충격'!$H$2:H4) -> -1749827.7 | I4: =IF(G4=0,0,G4/ABS(H4)) -> 0 | J4: =IF(AND(E4>0,G4>0),"구조적+시장위험",IF(E4>0,"구조적 유동성",IF(G4>0,"시장위험","충족"))) -> 충족
A5: 4월 | B5: =B4+'06_월별현금흐름'!C5+'06_월별현금흐름'!G5-'06_월별현금흐름'!H5-'06_월별현금흐름'!I5 -> 21500322 | C5: =B5+SUM('12_월별시장충격'!$H$2:H5) -> 18963892 | D5: ='05_재무입력'!$B$9 -> 10500000 | E5: =MAX(0,D5-B5) -> 0 | F5: =MAX(0,D5-C5) -> 0 | G5: =MAX(0,F5-E5) -> 0 | H5: =SUM('12_월별시장충격'!$H$2:H5) -> -2536430 | I5: =IF(G5=0,0,G5/ABS(H5)) -> 0 | J5: =IF(AND(E5>0,G5>0),"구조적+시장위험",IF(E5>0,"구조적 유동성",IF(G5>0,"시장위험","충족"))) -> 충족
A6: 5월 | B6: =B5+'06_월별현금흐름'!C6+'06_월별현금흐름'!G6-'06_월별현금흐름'!H6-'06_월별현금흐름'!I6 -> 22563707 | C6: =B6+SUM('12_월별시장충격'!$H$2:H6) -> 19416226 | D6: ='05_재무입력'!$B$9 -> 10500000 | E6: =MAX(0,D6-B6) -> 0 | F6: =MAX(0,D6-C6) -> 0 | G6: =MAX(0,F6-E6) -> 0 | H6: =SUM('12_월별시장충격'!$H$2:H6) -> -3147481.3 | I6: =IF(G6=0,0,G6/ABS(H6)) -> 0 | J6: =IF(AND(E6>0,G6>0),"구조적+시장위험",IF(E6>0,"구조적 유동성",IF(G6>0,"시장위험","충족"))) -> 충족
A7: 6월 | B7: =B6+'06_월별현금흐름'!C7+'06_월별현금흐름'!G7-'06_월별현금흐름'!H7-'06_월별현금흐름'!I7 -> 17170956 | C7: =B7+SUM('12_월별시장충격'!$H$2:H7) -> 13503386 | D7: ='05_재무입력'!$B$9 -> 10500000 | E7: =MAX(0,D7-B7) -> 0 | F7: =MAX(0,D7-C7) -> 0 | G7: =MAX(0,F7-E7) -> 0 | H7: =SUM('12_월별시장충격'!$H$2:H7) -> -3667569.5 | I7: =IF(G7=0,0,G7/ABS(H7)) -> 0 | J7: =IF(AND(E7>0,G7>0),"구조적+시장위험",IF(E7>0,"구조적 유동성",IF(G7>0,"시장위험","충족"))) -> 충족
A8: 7월 | B8: =B7+'06_월별현금흐름'!C8+'06_월별현금흐름'!G8-'06_월별현금흐름'!H8-'06_월별현금흐름'!I8 -> 18234340 | C8: =B8+SUM('12_월별시장충격'!$H$2:H8) -> 13948083 | D8: ='05_재무입력'!$B$9 -> 10500000 | E8: =MAX(0,D8-B8) -> 0 | F8: =MAX(0,D8-C8) -> 0 | G8: =MAX(0,F8-E8) -> 0 | H8: =SUM('12_월별시장충격'!$H$2:H8) -> -4286257.7 | I8: =IF(G8=0,0,G8/ABS(H8)) -> 0 | J8: =IF(AND(E8>0,G8>0),"구조적+시장위험",IF(E8>0,"구조적 유동성",IF(G8>0,"시장위험","충족"))) -> 충족
A9: 8월 | B9: =B8+'06_월별현금흐름'!C9+'06_월별현금흐름'!G9-'06_월별현금흐름'!H9-'06_월별현금흐름'!I9 -> 19297726 | C9: =B9+SUM('12_월별시장충격'!$H$2:H9) -> 14400416 | D9: ='05_재무입력'!$B$9 -> 10500000 | E9: =MAX(0,D9-B9) -> 0 | F9: =MAX(0,D9-C9) -> 0 | G9: =MAX(0,F9-E9) -> 0 | H9: =SUM('12_월별시장충격'!$H$2:H9) -> -4897309 | I9: =IF(G9=0,0,G9/ABS(H9)) -> 0 | J9: =IF(AND(E9>0,G9>0),"구조적+시장위험",IF(E9>0,"구조적 유동성",IF(G9>0,"시장위험","충족"))) -> 충족
A10: 9월 | B10: =B9+'06_월별현금흐름'!C10+'06_월별현금흐름'!G10-'06_월별현금흐름'!H10-'06_월별현금흐름'!I10 -> 17292360 | C10: =B10+SUM('12_월별시장충격'!$H$2:H10) -> 11874963 | D10: ='05_재무입력'!$B$9 -> 10500000 | E10: =MAX(0,D10-B10) -> 0 | F10: =MAX(0,D10-C10) -> 0 | G10: =MAX(0,F10-E10) -> 0 | H10: =SUM('12_월별시장충격'!$H$2:H10) -> -5417397.2 | I10: =IF(G10=0,0,G10/ABS(H10)) -> 0 | J10: =IF(AND(E10>0,G10>0),"구조적+시장위험",IF(E10>0,"구조적 유동성",IF(G10>0,"시장위험","충족"))) -> 충족
A11: 10월 | B11: =B10+'06_월별현금흐름'!C11+'06_월별현금흐름'!G11-'06_월별현금흐름'!H11-'06_월별현금흐름'!I11 -> 18355746 | C11: =B11+SUM('12_월별시장충격'!$H$2:H11) -> 12319660 | D11: ='05_재무입력'!$B$9 -> 10500000 | E11: =MAX(0,D11-B11) -> 0 | F11: =MAX(0,D11-C11) -> 0 | G11: =MAX(0,F11-E11) -> 0 | H11: =SUM('12_월별시장충격'!$H$2:H11) -> -6036085.4 | I11: =IF(G11=0,0,G11/ABS(H11)) -> 0 | J11: =IF(AND(E11>0,G11>0),"구조적+시장위험",IF(E11>0,"구조적 유동성",IF(G11>0,"시장위험","충족"))) -> 충족
A12: 11월 | B12: =B11+'06_월별현금흐름'!C12+'06_월별현금흐름'!G12-'06_월별현금흐름'!H12-'06_월별현금흐름'!I12 -> 19419130 | C12: =B12+SUM('12_월별시장충격'!$H$2:H12) -> 12771994 | D12: ='05_재무입력'!$B$9 -> 10500000 | E12: =MAX(0,D12-B12) -> 0 | F12: =MAX(0,D12-C12) -> 0 | G12: =MAX(0,F12-E12) -> 0 | H12: =SUM('12_월별시장충격'!$H$2:H12) -> -6647136.7 | I12: =IF(G12=0,0,G12/ABS(H12)) -> 0 | J12: =IF(AND(E12>0,G12>0),"구조적+시장위험",IF(E12>0,"구조적 유동성",IF(G12>0,"시장위험","충족"))) -> 충족
A13: 12월 | B13: =B12+'06_월별현금흐름'!C13+'06_월별현금흐름'!G13-'06_월별현금흐름'!H13-'06_월별현금흐름'!I13 -> 14026379 | C13: =B13+SUM('12_월별시장충격'!$H$2:H13) -> 7027068.2 | D13: ='05_재무입력'!$B$9 -> 10500000 | E13: =MAX(0,D13-B13) -> 0 | F13: =MAX(0,D13-C13) -> 3472931.8 | G13: =MAX(0,F13-E13) -> 3472931.8 | H13: =SUM('12_월별시장충격'!$H$2:H13) -> -6999310.8 | I13: =IF(G13=0,0,G13/ABS(H13)) -> 0.49618197 | J13: =IF(AND(E13>0,G13>0),"구조적+시장위험",IF(E13>0,"구조적 유동성",IF(G13>0,"시장위험","충족"))) -> 시장위험

Sheet 14_헤지상품매핑
A1: 노출ID | B1: 물리노출 | C1: MVP 사용시장변수 | D1: MVP 분석목적 | E1: 향후 헤지상품 후보1 | F1: 후보2 | G1: 후보3 | H1: 헤지방향 | I1: MVP 산출값 | J1: 현재 한계 | K1: 선정 후 고도화 | L1: 비고
A2: A | B2: P5TC 연동 TC-out 운임 | C2: KOBC Panamax TC 변동률을 Panamax 시장충격 Proxy로 사용 | D2: P5TC 연동 수입의 시장충격·필요 보호수준 산정 | E2: P5TC Future | H2: 매도 | I2: 필요 보호수준 | J2: 실제 P5TC FFA 역사 가격 미연결 | K2: 실제 FFA 가격·Basis·증거금 반영 후 계약수량 산정 | L2: MVP는 시장위험 진단에 집중
A3: C1 | B3: PNW→Japan Voyage 운임 | C3: USDA PNW→Japan 실제 운임 | D3: 실제 물리운임 하락 시 현금흐름 충격 산정 | E3: P3E_82 Future | F3: P5TC Future | H3: 매도 | I3: 필요 보호수준 | J3: 실제 FFA 가격 미연결 | K3: 후보별 OLS Hedge Ratio·Hedge Effectiveness 비교 | L3: 공개 실제 물리운임 사용
A4: C2 | B4: US Gulf→Japan Voyage 운임 | C4: USDA US Gulf→Japan 실제 운임 | D4: 실제 물리운임 하락 시 현금흐름 충격 산정 | E4: P2E_82 Future | F4: P6_82 Future | G4: P5TC Future | H4: 매도 | I4: 필요 보호수준 | J4: 실제 FFA 가격 미연결 | K4: 후보별 OLS·Basis Risk 비교 | L4: 공개 실제 물리운임 사용
A5: D | B5: Panamax 미래 TC-in 조달비 | C5: KOBC Panamax TC Average | D5: 시장 용선료 상승에 따른 조달비 충격 산정 | E5: P6_82 Future | F5: P2E_82 Future | G5: P5TC Future | H5: 매수 | I5: 필요 보호수준 | J5: 실제 FFA 가격 미연결 | K5: 실제 FFA와 KOBC TC 간 최적 Hedge Ratio 산정 | L5: 공개 Panamax 시장지수 사용
A6: FUEL_C1 | B6: PNW VLSFO 구매 | C6: Brent Spot 변동률 | D6: 연료비 상승 Stress Proxy | E6: Brent Crude Futures | H6: 매수 | I6: 필요 보호수준 | J6: VLSFO-Brent Basis Risk | K6: VLSFO 현물·연료파생상품 데이터로 Cross-hedge 재산정 | L6: MVP는 공개데이터 재현성 우선
A7: FUEL_C2 | B7: USGC VLSFO 구매 | C7: Brent Spot 변동률 | D7: 연료비 상승 Stress Proxy | E7: Brent Crude Futures | H7: 매수 | I7: 필요 보호수준 | J7: VLSFO-Brent Basis Risk | K7: USGC Marine Fuel 등 실제상품으로 고도화 | L7: MVP는 공개데이터 재현성 우선
A8: FUEL_D | B8: USGC VLSFO 구매 | C8: Brent Spot 변동률 | D8: 연료비 상승 Stress Proxy | E8: Brent Crude Futures | H8: 매수 | I8: 필요 보호수준 | J8: VLSFO-Brent Basis Risk | K8: USGC Marine Fuel 등 실제상품으로 고도화 | L8: COA 수행용 연료위험

Sheet 15_시장데이터
A1: 월 | B1: PNW→Japan 운임 (USD/t) | C1: US Gulf→Japan 운임 (USD/t) | D1: KOBC Panamax TC Average (USD/day) | E1: Brent Spot (USD/bbl) | G1: 항목 | H1: 출처/처리
A2: 44621 | B2: 42.85 | C2: 76.3 | D2: 28769.24 | E2: 117.25 | G2: 분석기간 | H2: 2022-03 ~ 2025-12 (46개월)
A3: 44652 | B3: 44.25 | C3: 78.5 | D3: 26716.19 | E3: 104.58 | G3: PNW→Japan | H3: USDA AMS Grain Transportation Report / Open AgTransport
A4: 44682 | B4: 46.25 | C4: 81.38 | D4: 29573.14 | E4: 113.34 | G4: US Gulf→Japan | H4: USDA AMS Grain Transportation Report / Open AgTransport
A5: 44713 | B5: 45.1 | C5: 78.95 | D5: 25559.2 | E5: 122.71 | G5: Panamax TC | H5: 사용자 업로드 KOBC 일별 PANAMAX 자료의 TC Average를 월평균
A6: 44743 | B6: 41.31 | C6: 70.88 | D6: 20054.29 | E6: 111.93 | G6: Brent | H6: U.S. EIA Europe Brent Spot Price 월별 시계열
A7: 44774 | B7: 37.38 | C7: 64.13 | D7: 17004.91 | E7: 100.45 | G7: USDA URL | H7: https://agtransport.usda.gov/Bulk/Bulk-Grain-Ocean-Freight-Rates/ehic-wtxb
A8: 44805 | B8: 35.1 | C8: 59.7 | D8: 17444.4 | E8: 89.76 | G8: KOBC URL | H8: https://www.kobc.or.kr/ebz/shippinginfo/panamax/gridList.do?mId=0301000000
A9: 44835 | B9: 36.38 | C9: 62.56 | D9: 19609.26 | E9: 93.33 | G9: EIA URL | H9: https://www.eia.gov/dnav/pet/hist/leafhandler.ashx?f=m&n=pet&s=rbrte
A10: 44866 | B10: 33.75 | C10: 57.83 | D10: 15318.95 | E10: 91.42 | G10: MVP 원칙 | H10: 실제 공개 현물/운임지수로 시장위험과 필요 보호수준을 산정
A11: 44896 | B11: 31.94 | C11: 56.81 | D11: 14657.65 | E11: 80.92 | G11: 향후 | H11: EEX/Baltic FFA 및 VLSFO 실제 시장데이터 연결
A12: 44927 | B12: 28.81 | C12: 52.31 | D12: 10611.37 | E12: 82.5
A13: 44958 | B13: 27.06 | C13: 48.56 | D13: 9781.6 | E13: 82.59
A14: 44986 | B14: 29.3 | C14: 52.5 | D14: 14990.86 | E14: 78.43
A15: 45017 | B15: 30 | C15: 55.19 | D15: 15237.55 | E15: 84.64
A16: 45047 | B16: 28.56 | C16: 51.38 | D16: 12357.65 | E16: 75.47
A17: 45078 | B17: 26.5 | C17: 48.1 | D17: 10691.71 | E17: 74.84
A18: 45108 | B18: 25.44 | C18: 46.13 | D18: 9536.95 | E18: 80.11
A19: 45139 | B19: 27.1 | C19: 50.4 | D19: 11490.5 | E19: 86.15
A20: 45170 | B20: 29.75 | C20: 55.75 | D20: 14499.89 | E20: 93.72
A21: 45200 | B21: 29.94 | C21: 57.13 | D21: 15522.47 | E21: 90.6
A22: 45231 | B22: 29.94 | C22: 57.94 | D22: 16229.1 | E22: 82.94
A23: 45261 | B23: 32.17 | C23: 61.75 | D23: 18940.88 | E23: 77.63
... A47: 45992 | B47: 29.08 | C47: 55.75 | D47: 15672.83 | E47: 62.54

Sheet 16_역사변동분석
A1: 실제 과거시장 변동 분석 — MVP Stress 산정
A3: 월 | B3: PNW→Japan 월변화율 | C3: US Gulf→Japan 월변화율 | D3: KOBC TC 월변화율 | E3: Brent 월변화율 | G3: 위험요인 | H3: Stress 방향 | I3: 역사기준 | J3: MVP 적용충격률
A4: 44652 | B4: ='15_시장데이터'!B3/'15_시장데이터'!B2-1 -> 0.032672112 | C4: ='15_시장데이터'!C3/'15_시장데이터'!C2-1 -> 0.028833552 | D4: ='15_시장데이터'!D3/'15_시장데이터'!D2-1 -> -0.071362678 | E4: ='15_시장데이터'!E3/'15_시장데이터'!E2-1 -> -0.1080597 | G4: A Panamax 운임 | H4: 하락 | I4: KOBC 월변화율 하위 10% | J4: -0.20013719
A5: 44682 | B5: ='15_시장데이터'!B4/'15_시장데이터'!B3-1 -> 0.04519774 | C5: ='15_시장데이터'!C4/'15_시장데이터'!C3-1 -> 0.036687898 | D5: ='15_시장데이터'!D4/'15_시장데이터'!D3-1 -> 0.10693703 | E5: ='15_시장데이터'!E4/'15_시장데이터'!E3-1 -> 0.083763626 | G5: C1 PNW→Japan | H5: 하락 | I5: PNW 월변화율 하위 10% | J5: -0.071848739
A6: 44713 | B6: ='15_시장데이터'!B5/'15_시장데이터'!B4-1 -> -0.024864865 | C6: ='15_시장데이터'!C5/'15_시장데이터'!C4-1 -> -0.029859916 | D6: ='15_시장데이터'!D5/'15_시장데이터'!D4-1 -> -0.13572925 | E6: ='15_시장데이터'!E5/'15_시장데이터'!E4-1 -> 0.082671608 | G6: C2 USG→Japan | H6: 하락 | I6: USG 월변화율 하위 10% | J6: -0.07499408
A7: 44743 | B7: ='15_시장데이터'!B6/'15_시장데이터'!B5-1 -> -0.084035477 | C7: ='15_시장데이터'!C6/'15_시장데이터'!C5-1 -> -0.10221659 | D7: ='15_시장데이터'!D6/'15_시장데이터'!D5-1 -> -0.21537881 | E7: ='15_시장데이터'!E6/'15_시장데이터'!E5-1 -> -0.087849401 | G7: D TC-in 조달비 | H7: 상승 | I7: KOBC 월변화율 상위 10% | J7: 0.2274134
A8: 44774 | B8: ='15_시장데이터'!B7/'15_시장데이터'!B6-1 -> -0.09513435 | C8: ='15_시장데이터'!C7/'15_시장데이터'!C6-1 -> -0.095231377 | D8: ='15_시장데이터'!D7/'15_시장데이터'!D6-1 -> -0.15205624 | E8: ='15_시장데이터'!E7/'15_시장데이터'!E6-1 -> -0.1025641 | G8: 연료비 | H8: 상승 | I8: Brent 월변화율 상위 10% | J8: 0.077665863
A9: 44805 | B9: ='15_시장데이터'!B8/'15_시장데이터'!B7-1 -> -0.060995185 | C9: ='15_시장데이터'!C8/'15_시장데이터'!C7-1 -> -0.069078434 | D9: ='15_시장데이터'!D8/'15_시장데이터'!D7-1 -> 0.025844888 | E9: ='15_시장데이터'!E8/'15_시장데이터'!E7-1 -> -0.10642111
A10: 44835 | B10: ='15_시장데이터'!B9/'15_시장데이터'!B8-1 -> 0.036467236 | C10: ='15_시장데이터'!C9/'15_시장데이터'!C8-1 -> 0.047906198 | D10: ='15_시장데이터'!D9/'15_시장데이터'!D8-1 -> 0.12410057 | E10: ='15_시장데이터'!E9/'15_시장데이터'!E8-1 -> 0.039772727 | G10: Stress 정의: 2022-03~2025-12 실제 월별 변화율의 하위 10%(운임 하락) / 상위 10%(비용 상승)를 사용합니다. 최악의 한 달을 그대로 쓰지 않아 극단치 의존을 줄인 '역사적 스트레스'입니다.
A11: 44866 | B11: ='15_시장데이터'!B10/'15_시장데이터'!B9-1 -> -0.072292468 | C11: ='15_시장데이터'!C10/'15_시장데이터'!C9-1 -> -0.075607417 | D11: ='15_시장데이터'!D10/'15_시장데이터'!D9-1 -> -0.21879 | E11: ='15_시장데이터'!E10/'15_시장데이터'!E9-1 -> -0.020465017
A12: 44896 | B12: ='15_시장데이터'!B11/'15_시장데이터'!B10-1 -> -0.05362963 | C12: ='15_시장데이터'!C11/'15_시장데이터'!C10-1 -> -0.017637904 | D12: ='15_시장데이터'!D11/'15_시장데이터'!D10-1 -> -0.043168755 | E12: ='15_시장데이터'!E11/'15_시장데이터'!E10-1 -> -0.11485452
A13: 44927 | B13: ='15_시장데이터'!B12/'15_시장데이터'!B11-1 -> -0.097996243 | C13: ='15_시장데이터'!C12/'15_시장데이터'!C11-1 -> -0.079211406 | D13: ='15_시장데이터'!D12/'15_시장데이터'!D11-1 -> -0.27605244 | E13: ='15_시장데이터'!E12/'15_시장데이터'!E11-1 -> 0.019525457
A14: 44958 | B14: ='15_시장데이터'!B13/'15_시장데이터'!B12-1 -> -0.060742798 | C14: ='15_시장데이터'!C13/'15_시장데이터'!C12-1 -> -0.071688014 | D14: ='15_시장데이터'!D13/'15_시장데이터'!D12-1 -> -0.078196312 | E14: ='15_시장데이터'!E13/'15_시장데이터'!E12-1 -> 0.0010909091
A15: 44986 | B15: ='15_시장데이터'!B14/'15_시장데이터'!B13-1 -> 0.08277901 | C15: ='15_시장데이터'!C14/'15_시장데이터'!C13-1 -> 0.081136738 | D15: ='15_시장데이터'!D14/'15_시장데이터'!D13-1 -> 0.53255705 | E15: ='15_시장데이터'!E14/'15_시장데이터'!E13-1 -> -0.050369294
A16: 45017 | B16: ='15_시장데이터'!B15/'15_시장데이터'!B14-1 -> 0.023890785 | C16: ='15_시장데이터'!C15/'15_시장데이터'!C14-1 -> 0.051238095 | D16: ='15_시장데이터'!D15/'15_시장데이터'!D14-1 -> 0.016456027 | E16: ='15_시장데이터'!E15/'15_시장데이터'!E14-1 -> 0.079178886
A17: 45047 | B17: ='15_시장데이터'!B16/'15_시장데이터'!B15-1 -> -0.048 | C17: ='15_시장데이터'!C16/'15_시장데이터'!C15-1 -> -0.069034245 | D17: ='15_시장데이터'!D16/'15_시장데이터'!D15-1 -> -0.1890002 | E17: ='15_시장데이터'!E16/'15_시장데이터'!E15-1 -> -0.10834121
A18: 45078 | B18: ='15_시장데이터'!B17/'15_시장데이터'!B16-1 -> -0.072128852 | C18: ='15_시장데이터'!C17/'15_시장데이터'!C16-1 -> -0.063838069 | D18: ='15_시장데이터'!D17/'15_시장데이터'!D16-1 -> -0.13481042 | E18: ='15_시장데이터'!E17/'15_시장데이터'!E16-1 -> -0.0083476878
A19: 45108 | B19: ='15_시장데이터'!B18/'15_시장데이터'!B17-1 -> -0.04 | C19: ='15_시장데이터'!C18/'15_시장데이터'!C17-1 -> -0.040956341 | D19: ='15_시장데이터'!D18/'15_시장데이터'!D17-1 -> -0.10800517 | E19: ='15_시장데이터'!E18/'15_시장데이터'!E17-1 -> 0.070416889
A20: 45139 | B20: ='15_시장데이터'!B19/'15_시장데이터'!B18-1 -> 0.065251572 | C20: ='15_시장데이터'!C19/'15_시장데이터'!C18-1 -> 0.092564492 | D20: ='15_시장데이터'!D19/'15_시장데이터'!D18-1 -> 0.20484012 | E20: ='15_시장데이터'!E19/'15_시장데이터'!E18-1 -> 0.07539633
A21: 45170 | B21: ='15_시장데이터'!B20/'15_시장데이터'!B19-1 -> 0.097785978 | C21: ='15_시장데이터'!C20/'15_시장데이터'!C19-1 -> 0.10615079 | D21: ='15_시장데이터'!D20/'15_시장데이터'!D19-1 -> 0.26190244 | E21: ='15_시장데이터'!E20/'15_시장데이터'!E19-1 -> 0.087869994
A22: 45200 | B22: ='15_시장데이터'!B21/'15_시장데이터'!B20-1 -> 0.0063865546 | C22: ='15_시장데이터'!C21/'15_시장데이터'!C20-1 -> 0.024753363 | D22: ='15_시장데이터'!D21/'15_시장데이터'!D20-1 -> 0.070523294 | E22: ='15_시장데이터'!E21/'15_시장데이터'!E20-1 -> -0.033290653
... A48: 45992 | B48: ='15_시장데이터'!B47/'15_시장데이터'!B46-1 -> -0.0024013722 | C48: ='15_시장데이터'!C47/'15_시장데이터'!C46-1 -> -0.013274336 | D48: ='15_시장데이터'!D47/'15_시장데이터'!D46-1 -> -0.16616142 | E48: ='15_시장데이터'!E47/'15_시장데이터'!E46-1 -> -0.019749216

Sheet 17_보호전략
A1: 보호수준별 전략 비교 — 실제 FFA 가격 연결 전 MVP
A3: 전략 | B3: 시장위험 보호수준 | C3: 최저 월말현금 (USD) | D3: Floor 미달개월 | E3: 연말현금 (USD) | F3: 보호한 시장손실 (USD) | G3: 해석
A4: 무보호 | B4: 0 | C4: =MIN(B12:B23) -> 7027068.2 | D4: =COUNTIF(B12:B23,"<"&'05_재무입력'!$B$9) -> 1 | E4: =B23 -> 7027068.2 | F4: =ABS('13_Need 진단'!$H$13)*B4 -> 0 | G4: =IF(D4=0,"Floor 충족",IF(B4=1,"시장위험 제거 후 구조적 부족 잔존","Floor 미달 "&D4&"개월")) -> Floor 미달 1개월
A5: 부분보호 30% | B5: 0.3 | C5: =MIN(C12:C23) -> 9126861.5 | D5: =COUNTIF(C12:C23,"<"&'05_재무입력'!$B$9) -> 1 | E5: =C23 -> 9126861.5 | F5: =ABS('13_Need 진단'!$H$13)*B5 -> 2099793.2 | G5: =IF(D5=0,"Floor 충족",IF(B5=1,"시장위험 제거 후 구조적 부족 잔존","Floor 미달 "&D5&"개월")) -> Floor 미달 1개월
A6: 균형보호 50% | B6: 0.5 | C6: =MIN(D12:D23) -> 10526724 | D6: =COUNTIF(D12:D23,"<"&'05_재무입력'!$B$9) -> 0 | E6: =D23 -> 10526724 | F6: =ABS('13_Need 진단'!$H$13)*B6 -> 3499655.4 | G6: =IF(D6=0,"Floor 충족",IF(B6=1,"시장위험 제거 후 구조적 부족 잔존","Floor 미달 "&D6&"개월")) -> Floor 충족
A7: 안정성보호 70% | B7: 0.7 | C7: =MIN(E12:E23) -> 11926586 | D7: =COUNTIF(E12:E23,"<"&'05_재무입력'!$B$9) -> 0 | E7: =E23 -> 11926586 | F7: =ABS('13_Need 진단'!$H$13)*B7 -> 4899517.5 | G7: =IF(D7=0,"Floor 충족",IF(B7=1,"시장위험 제거 후 구조적 부족 잔존","Floor 미달 "&D7&"개월")) -> Floor 충족
A8: 시장위험 100% 보호 | B8: 1 | C8: =MIN(F12:F23) -> 14026379 | D8: =COUNTIF(F12:F23,"<"&'05_재무입력'!$B$9) -> 0 | E8: =F23 -> 14026379 | F8: =ABS('13_Need 진단'!$H$13)*B8 -> 6999310.8 | G8: =IF(D8=0,"Floor 충족",IF(B8=1,"시장위험 제거 후 구조적 부족 잔존","Floor 미달 "&D8&"개월")) -> Floor 충족
A11: 월 | B11: 무보호 | C11: 부분보호 30% | D11: 균형보호 50% | E11: 안정성보호 70% | F11: 시장위험 100% 보호
A12: ='13_Need 진단'!A2 -> 1월 | B12: ='13_Need 진단'!B2+'13_Need 진단'!H2*(1-0) -> 20592315 | C12: ='13_Need 진단'!B2+'13_Need 진단'!H2*(1-0.3) -> 20828295 | D12: ='13_Need 진단'!B2+'13_Need 진단'!H2*(1-0.5) -> 20985616 | E12: ='13_Need 진단'!B2+'13_Need 진단'!H2*(1-0.7) -> 21142936 | F12: ='13_Need 진단'!B2+'13_Need 진단'!H2*(1-1) -> 21378917
A13: ='13_Need 진단'!A3 -> 2월 | B13: ='13_Need 진단'!B3+'13_Need 진단'!H3*(1-0) -> 21044648 | C13: ='13_Need 진단'!B3+'13_Need 진단'!H3*(1-0.3) -> 21463944 | D13: ='13_Need 진단'!B3+'13_Need 진단'!H3*(1-0.5) -> 21743475 | E13: ='13_Need 진단'!B3+'13_Need 진단'!H3*(1-0.7) -> 22023006 | F13: ='13_Need 진단'!B3+'13_Need 진단'!H3*(1-1) -> 22442302
A14: ='13_Need 진단'!A4 -> 3월 | B14: ='13_Need 진단'!B4+'13_Need 진단'!H4*(1-0) -> 18687109 | C14: ='13_Need 진단'!B4+'13_Need 진단'!H4*(1-0.3) -> 19212058 | D14: ='13_Need 진단'!B4+'13_Need 진단'!H4*(1-0.5) -> 19562023 | E14: ='13_Need 진단'!B4+'13_Need 진단'!H4*(1-0.7) -> 19911989 | F14: ='13_Need 진단'!B4+'13_Need 진단'!H4*(1-1) -> 20436937
A15: ='13_Need 진단'!A5 -> 4월 | B15: ='13_Need 진단'!B5+'13_Need 진단'!H5*(1-0) -> 18963892 | C15: ='13_Need 진단'!B5+'13_Need 진단'!H5*(1-0.3) -> 19724821 | D15: ='13_Need 진단'!B5+'13_Need 진단'!H5*(1-0.5) -> 20232107 | E15: ='13_Need 진단'!B5+'13_Need 진단'!H5*(1-0.7) -> 20739393 | F15: ='13_Need 진단'!B5+'13_Need 진단'!H5*(1-1) -> 21500322
A16: ='13_Need 진단'!A6 -> 5월 | B16: ='13_Need 진단'!B6+'13_Need 진단'!H6*(1-0) -> 19416226 | C16: ='13_Need 진단'!B6+'13_Need 진단'!H6*(1-0.3) -> 20360470 | D16: ='13_Need 진단'!B6+'13_Need 진단'!H6*(1-0.5) -> 20989966 | E16: ='13_Need 진단'!B6+'13_Need 진단'!H6*(1-0.7) -> 21619463 | F16: ='13_Need 진단'!B6+'13_Need 진단'!H6*(1-1) -> 22563707
A17: ='13_Need 진단'!A7 -> 6월 | B17: ='13_Need 진단'!B7+'13_Need 진단'!H7*(1-0) -> 13503386 | C17: ='13_Need 진단'!B7+'13_Need 진단'!H7*(1-0.3) -> 14603657 | D17: ='13_Need 진단'!B7+'13_Need 진단'!H7*(1-0.5) -> 15337171 | E17: ='13_Need 진단'!B7+'13_Need 진단'!H7*(1-0.7) -> 16070685 | F17: ='13_Need 진단'!B7+'13_Need 진단'!H7*(1-1) -> 17170956
A18: ='13_Need 진단'!A8 -> 7월 | B18: ='13_Need 진단'!B8+'13_Need 진단'!H8*(1-0) -> 13948083 | C18: ='13_Need 진단'!B8+'13_Need 진단'!H8*(1-0.3) -> 15233960 | D18: ='13_Need 진단'!B8+'13_Need 진단'!H8*(1-0.5) -> 16091212 | E18: ='13_Need 진단'!B8+'13_Need 진단'!H8*(1-0.7) -> 16948463 | F18: ='13_Need 진단'!B8+'13_Need 진단'!H8*(1-1) -> 18234340
A19: ='13_Need 진단'!A9 -> 8월 | B19: ='13_Need 진단'!B9+'13_Need 진단'!H9*(1-0) -> 14400416 | C19: ='13_Need 진단'!B9+'13_Need 진단'!H9*(1-0.3) -> 15869609 | D19: ='13_Need 진단'!B9+'13_Need 진단'!H9*(1-0.5) -> 16849071 | E19: ='13_Need 진단'!B9+'13_Need 진단'!H9*(1-0.7) -> 17828533 | F19: ='13_Need 진단'!B9+'13_Need 진단'!H9*(1-1) -> 19297726
A20: ='13_Need 진단'!A10 -> 9월 | B20: ='13_Need 진단'!B10+'13_Need 진단'!H10*(1-0) -> 11874963 | C20: ='13_Need 진단'!B10+'13_Need 진단'!H10*(1-0.3) -> 13500182 | D20: ='13_Need 진단'!B10+'13_Need 진단'!H10*(1-0.5) -> 14583662 | E20: ='13_Need 진단'!B10+'13_Need 진단'!H10*(1-0.7) -> 15667141 | F20: ='13_Need 진단'!B10+'13_Need 진단'!H10*(1-1) -> 17292360
A21: ='13_Need 진단'!A11 -> 10월 | B21: ='13_Need 진단'!B11+'13_Need 진단'!H11*(1-0) -> 12319660 | C21: ='13_Need 진단'!B11+'13_Need 진단'!H11*(1-0.3) -> 14130486 | D21: ='13_Need 진단'!B11+'13_Need 진단'!H11*(1-0.5) -> 15337703 | E21: ='13_Need 진단'!B11+'13_Need 진단'!H11*(1-0.7) -> 16544920 | F21: ='13_Need 진단'!B11+'13_Need 진단'!H11*(1-1) -> 18355746
A22: ='13_Need 진단'!A12 -> 11월 | B22: ='13_Need 진단'!B12+'13_Need 진단'!H12*(1-0) -> 12771994 | C22: ='13_Need 진단'!B12+'13_Need 진단'!H12*(1-0.3) -> 14766135 | D22: ='13_Need 진단'!B12+'13_Need 진단'!H12*(1-0.5) -> 16095562 | E22: ='13_Need 진단'!B12+'13_Need 진단'!H12*(1-0.7) -> 17424989 | F22: ='13_Need 진단'!B12+'13_Need 진단'!H12*(1-1) -> 19419130
A23: ='13_Need 진단'!A13 -> 12월 | B23: ='13_Need 진단'!B13+'13_Need 진단'!H13*(1-0) -> 7027068.2 | C23: ='13_Need 진단'!B13+'13_Need 진단'!H13*(1-0.3) -> 9126861.5 | D23: ='13_Need 진단'!B13+'13_Need 진단'!H13*(1-0.5) -> 10526724 | E23: ='13_Need 진단'!B13+'13_Need 진단'!H13*(1-0.7) -> 11926586 | F23: ='13_Need 진단'!B13+'13_Need 진단'!H13*(1-1) -> 14026379
A26: 보호수준은 '실제 FFA 계약비율'이 아니라 시장충격 중 경제적으로 상쇄하는 비율입니다. 향후 EEX/Baltic FFA 가격을 연결하면 이 보호수준을 실제 Hedge Ratio와 계약수량으로 변환합니다.

Sheet 18_Capacity
A1: Capacity 진단 — 실제 증거금 데이터 연결 전 유동성 여력
A3: 입력/지표 | B3: 금액 (USD)
A4: 추가 확보 유동성 | B4: 0
A5: 최소유동성 Floor | B5: ='05_재무입력'!B9 -> 10500000
A8: 전략 | B8: 보호수준 | C8: 보호 후 최저현금 | D8: 추가유동성 반영 최저현금 | E8: Floor 대비 여유 | F8: 흡수가능 임시담보/증거금 | G8: Capacity 판단
A9: ='17_보호전략'!A4 -> 무보호 | B9: ='17_보호전략'!B4 -> 0 | C9: ='17_보호전략'!C4 -> 7027068.2 | D9: =C9+$B$4 -> 7027068.2 | E9: =D9-$B$5 -> -3472931.8 | F9: =MAX(0,E9) -> 0 | G9: =IF(E9>0,"실제 Margin이 "&TEXT(F9,"#,##0")&" 이하이면 실행 가능",IF(E9=0,"Floor만 충족: Margin 여력 없음","현재 구조에서는 실행 불가")) -> 현재 구조에서는 실행 불가
A10: ='17_보호전략'!A5 -> 부분보호 30% | B10: ='17_보호전략'!B5 -> 0.3 | C10: ='17_보호전략'!C5 -> 9126861.5 | D10: =C10+$B$4 -> 9126861.5 | E10: =D10-$B$5 -> -1373138.5 | F10: =MAX(0,E10) -> 0 | G10: =IF(E10>0,"실제 Margin이 "&TEXT(F10,"#,##0")&" 이하이면 실행 가능",IF(E10=0,"Floor만 충족: Margin 여력 없음","현재 구조에서는 실행 불가")) -> 현재 구조에서는 실행 불가
A11: ='17_보호전략'!A6 -> 균형보호 50% | B11: ='17_보호전략'!B6 -> 0.5 | C11: ='17_보호전략'!C6 -> 10526724 | D11: =C11+$B$4 -> 10526724 | E11: =D11-$B$5 -> 26723.608 | F11: =MAX(0,E11) -> 26723.608 | G11: =IF(E11>0,"실제 Margin이 "&TEXT(F11,"#,##0")&" 이하이면 실행 가능",IF(E11=0,"Floor만 충족: Margin 여력 없음","현재 구조에서는 실행 불가")) -> 실제 Margin이 26,724 이하이면 실행 가능
A12: ='17_보호전략'!A7 -> 안정성보호 70% | B12: ='17_보호전략'!B7 -> 0.7 | C12: ='17_보호전략'!C7 -> 11926586 | D12: =C12+$B$4 -> 11926586 | E12: =D12-$B$5 -> 1426585.8 | F12: =MAX(0,E12) -> 1426585.8 | G12: =IF(E12>0,"실제 Margin이 "&TEXT(F12,"#,##0")&" 이하이면 실행 가능",IF(E12=0,"Floor만 충족: Margin 여력 없음","현재 구조에서는 실행 불가")) -> 실제 Margin이 1,426,586 이하이면 실행 가능
A13: ='17_보호전략'!A8 -> 시장위험 100% 보호 | B13: ='17_보호전략'!B8 -> 1 | C13: ='17_보호전략'!C8 -> 14026379 | D13: =C13+$B$4 -> 14026379 | E13: =D13-$B$5 -> 3526379 | F13: =MAX(0,E13) -> 3526379 | G13: =IF(E13>0,"실제 Margin이 "&TEXT(F13,"#,##0")&" 이하이면 실행 가능",IF(E13=0,"Floor만 충족: Margin 여력 없음","현재 구조에서는 실행 불가")) -> 실제 Margin이 3,526,379 이하이면 실행 가능
A16: Capacity는 '헤지가 필요하다'와 별개의 문제입니다. 현재는 실제 거래소 Initial/Variation Margin 데이터가 없으므로, 각 보호전략을 적용한 뒤 Floor 위에 남는 현금을 '흡수 가능한 임시담보/증거금 한도'로 제시합니다. 선정 후 실제 FFA Margin 데이터를 연결해 이 한도와 직접 비교합니다.

Sheet 19_프로젝트요약
A1: BlueWave AI 해운 헤지 의사결정 MVP — 현재 구현범위
A3: 핵심항목 | B3: 현재 MVP | D3: 선정 후 고도화
A4: Exposure | B4: 계약별 운임·연료 노출을 월별로 산정 | D4: ① EEX/Baltic 실제 FFA 가격 연결 ② P5TC·P2E_82·P3E_82·P6_82 후보별 OLS Hedge Ratio 및 Hedge Effectiveness ③ 실제 VLSFO 및 Marine Fuel 파생상품 데이터 연결 ④ Initial/Variation Margin 및 담보 시차 반영 ⑤ Python/Web 서비스화 및 AI 자연어 인터페이스
A5: Need | B5: 실제 과거 운임/Brent 기반 역사적 Stress에서 Floor 미달 여부 진단
A6: Strategy | B6: 시장충격의 0/30/50/70/100% 보호수준별 현금흐름 비교
A7: Capacity | B7: 보호 후 Floor 위 잔여현금을 임시담보/증거금 흡수여력으로 계산
A8: AI 역할 | B8: 계약·경영목표 자연어 해석, 결과 설명, 리스크 경고
A9: 정량계산 | B9: 검증 가능한 재무·통계 로직이 수행
A12: 모형 해석 원칙
A13: 현재의 '보호수준'은 실제 FFA 계약비율이 아닙니다. 공개 가능한 실제 운임지수와 Brent를 이용해 회사가 시장충격 중 어느 정도를 경제적으로 상쇄해야 최소유동성을 유지하는지 계산합니다. 실제 FFA 데이터가 확보되면 보호수준을 실행 가능한 파생상품·Hedge Ratio·계약수량으로 변환합니다.
A19: 10/8 제출 전 남은 작업
A20: 순서 | B20: 작업
A21: 1 | B21: 통합모형 검산 및 결과값 해석
A22: 2 | B22: 대표 전략 2~3개 선정 및 사용자 화면 흐름 정리
A23: 3 | B23: AI가 맡는 부분과 금융모형이 맡는 부분 명확화
A24: 4 | B24: 지원서 1000자 문항들 작성
A25: 5 | B25: 멘토링 요청사항: FFA 데이터/API, Margin, 웹 구현, 모델 검증
